ifis/__init__.py
ifis/interval_aggregations.py
ifis/interval_fuzzy_sets.py
ifis/interval_fuzzy_system.py
ifis/interval_linguistic_variable.py
ifis/interval_rule_parsing.py
ifis-1.0.1.dist-info/METADATA
ifis-1.0.1.dist-info/WHEEL
ifis-1.0.1.dist-info/licenses/LICENSE
ifis-1.0.1.dist-info/RECORD
