Metadata-Version: 2.1
Name: ifis
Version: 1.0.1
Summary: A Python library for interval fuzzy logic
Project-URL: Homepage, https://github.com/PGrochowalski/ifis
Project-URL: Issues, https://github.com/PGrochowalski/ifis/issues
Author-email: Piotr Grochowalski <pgrochowalski@ur.edu.pl>
License-File: LICENSE
Classifier: License :: OSI Approved :: GNU General Public License v3 (GPLv3)
Classifier: Operating System :: OS Independent
Classifier: Programming Language :: Python :: 3
Requires-Python: >=3.8
Requires-Dist: matplotlib>=3.5.1
Requires-Dist: numpy>=1.12.0
Requires-Dist: scipy>=1.0.0
Requires-Dist: seaborn>=0.11.2
Requires-Dist: simpful>=2.1.1
